colorconversion/__init__.py
colorconversion-0.1.2.dist-info/LICENSE
colorconversion-0.1.2.dist-info/METADATA
colorconversion-0.1.2.dist-info/WHEEL
colorconversion-0.1.2.dist-info/top_level.txt
colorconversion-0.1.2.dist-info/RECORD
